tapi/__init__.py
tapi/__main__.py
tapi/translateapi.py
ydtapi-2.0.dist-info/LICENSE
ydtapi-2.0.dist-info/METADATA
ydtapi-2.0.dist-info/WHEEL
ydtapi-2.0.dist-info/top_level.txt
ydtapi-2.0.dist-info/RECORD
