Metadata-Version: 2.1
Name: ydtapi
Version: 2.0
Summary: Youdao translate API for python
Home-page: UNKNOWN
Author: UNKNOWN
Author-email: UNKNOWN
License: none
Platform: posix
Requires-Dist: requests
